libname/__init__.py
libname/calculator.py
sameer_simple_calculator-1.0.2.dist-info/METADATA
sameer_simple_calculator-1.0.2.dist-info/WHEEL
sameer_simple_calculator-1.0.2.dist-info/top_level.txt
sameer_simple_calculator-1.0.2.dist-info/RECORD
