Metadata-Version: 2.1
Name: sameer-simple-calculator
Version: 1.0.2
Summary: Simple Calculator Package
Home-page: UNKNOWN
Author: Muhammad Sameer
Author-email: muhammadsameer.css@gmail.com
License: UNKNOWN
Keywords: python,calculator,python calculator,cli
Platform: UNKNOWN
Classifier: Development Status :: 1 - Planning
Classifier: Intended Audience :: Developers
Classifier: Programming Language :: Python :: 3
Classifier: Operating System :: Unix
Classifier: Operating System :: MacOS :: MacOS X
Classifier: Operating System :: Microsoft :: Windows
Requires-Python: >=3.6
